monai_nvflare/__init__.py
monai_nvflare/client_algo_executor.py
monai_nvflare/client_algo_statistics.py
monai_nvflare/monai_bundle_persistor.py
monai_nvflare/monai_data_stats_persistor.py
monai_nvflare/nvflare_stats_handler.py
monai_nvflare/utils.py
monai_nvflare-0.4.0.dist-info/METADATA
monai_nvflare-0.4.0.dist-info/WHEEL
monai_nvflare-0.4.0.dist-info/top_level.txt
monai_nvflare-0.4.0.dist-info/RECORD
