Metadata-Version: 2.4
Name: monai-nvflare
Version: 0.4.0
Summary: MONAI NVIDIA FLARE integration
Home-page: https://github.com/NVIDIA/NVFlare
Classifier: Programming Language :: Python :: 3.9
Classifier: Programming Language :: Python :: 3.10
Classifier: Programming Language :: Python :: 3.11
Classifier: License :: OSI Approved :: Apache Software License
Classifier: Operating System :: POSIX :: Linux
Requires-Python: >=3.9,<3.12
Requires-Dist: monai>=1.3.1
Requires-Dist: nvflare~=2.7.0rc
Dynamic: classifier
Dynamic: description
Dynamic: description-content-type
Dynamic: home-page
Dynamic: requires-dist
Dynamic: requires-python
Dynamic: summary
